tcxparser/__init__.py
tcxparser/tcxparser.py
dpac_tcxparser-1.0.1.dist-info/AUTHORS.rst
dpac_tcxparser-1.0.1.dist-info/LICENSE
dpac_tcxparser-1.0.1.dist-info/METADATA
dpac_tcxparser-1.0.1.dist-info/WHEEL
dpac_tcxparser-1.0.1.dist-info/top_level.txt
dpac_tcxparser-1.0.1.dist-info/RECORD
