Metadata-Version: 2.1
Name: dpac-tcxparser
Version: 1.0.1
Summary: Simple parser for Garmin/Polar TCX files
Home-page: https://github.com/davidpch/python-tcxparser/
Author: David Pacheco & Vinod Kurup
Author-email: vinod@kurup.com
License: BSD
Keywords: tcx
Platform: UNKNOWN
Classifier: Development Status :: 5 - Production/Stable
Classifier: Intended Audience :: Developers
Classifier: License :: OSI Approved :: BSD License
Classifier: Operating System :: OS Independent
Classifier: Programming Language :: Python
Classifier: Programming Language :: Python :: 2
Classifier: Programming Language :: Python :: 2.7
Classifier: Programming Language :: Python :: 3
Classifier: Programming Language :: Python :: 3.6
Classifier: Topic :: Software Development :: Libraries :: Python Modules
Requires-Dist: lxml
